microfreshener/__init__.py
microfreshener/command_line.py
microfreshener/core/__init__.py
microfreshener/core/errors.py
microfreshener/core/logging.py
microfreshener/core/analyser/__init__.py
microfreshener/core/analyser/analyser.py
microfreshener/core/analyser/builder.py
microfreshener/core/analyser/constant.py
microfreshener/core/analyser/costants.py
microfreshener/core/analyser/refactorings.py
microfreshener/core/analyser/smell.py
microfreshener/core/analyser/sniffer.py
microfreshener/core/exporter/__init__.py
microfreshener/core/exporter/iexporter.py
microfreshener/core/exporter/jsonexporter.py
microfreshener/core/exporter/ymlexporter.py
microfreshener/core/helper/__init__.py
microfreshener/core/helper/decorator.py
microfreshener/core/importer/__init__.py
microfreshener/core/importer/iimporter.py
microfreshener/core/importer/jsonimporter.py
microfreshener/core/importer/jsontype.py
microfreshener/core/importer/ymlimporter.py
microfreshener/core/importer/ymltype.py
microfreshener/core/model/__init__.py
microfreshener/core/model/groups.py
microfreshener/core/model/microtosca.py
microfreshener/core/model/nodes.py
microfreshener/core/model/relationships.py
microfreshener/core/model/type.py
microfreshener/core/refiner/__init__.py
microfreshener/core/refiner/irefiner.py
microfreshener/core/refiner/istiorefiner.py
microfreshener/core/refiner/kubernetesrefiner.py
tests/test_analyser/__init__.py
tests/test_analyser/test_analyser.py
tests/test_analyser/test_builder.py
tests/test_analyser/test_sniffer_ebsi.py
tests/test_analyser/test_sniffer_msioc.py
tests/test_analyser/test_sniffer_nagw.py
tests/test_analyser/test_sniffer_sbc.py
tests/test_analyser/test_sniffer_shpr.py
tests/test_analyser/test_sniffer_slt.py
tests/test_analyser/test_sniffer_tct.py
tests/test_analyser/test_sniffer_wbsi.py
tests/test_analyser/log/log_2024-04-05.log
tests/test_exporter/__init__.py
tests/test_exporter/test_export_json.py
tests/test_exporter/test_export_json_nodes.py
microfreshener_core-1.5.0.dist-info/LICENSE
microfreshener_core-1.5.0.dist-info/METADATA
microfreshener_core-1.5.0.dist-info/WHEEL
microfreshener_core-1.5.0.dist-info/entry_points.txt
microfreshener_core-1.5.0.dist-info/top_level.txt
microfreshener_core-1.5.0.dist-info/RECORD
