Metadata-Version: 2.1
Name: microfreshener-core
Version: 1.5.0
Summary: Read a MicroTOSCA model of a microservice-based architecture and discover architectural smells
Home-page: 
Author: Davide neri
Author-email: davide.neri@di.unipi.it
License: MIT
Keywords: microservice TOSCA smells refactorings
License-File: LICENSE
Requires-Dist: ruamel.yaml
Requires-Dist: tosca-parser
